testaton/__init__.py
testaton/__main__.py
testaton/cli.py
testaton/common_functions.py
testaton/generate_sql.py
testaton/main.py
testaton/test_executor.py
testaton/tests_processor.py
testaton/tests/__init__.py
testaton/tests/test_ext_integration.py
testaton/tests/test_generate_sql.py
testaton/tests/unit_test.py
testaton-0.1.13.dist-info/METADATA
testaton-0.1.13.dist-info/WHEEL
testaton-0.1.13.dist-info/entry_points.txt
testaton-0.1.13.dist-info/top_level.txt
testaton-0.1.13.dist-info/RECORD
