Metadata-Version: 2.1
Name: testaton
Version: 0.1.13
Summary: A command line tool to allow the testing of datasets
Home-page: https://github.com/mikelupu/testaton
Author: Michael Farrugia
Author-email: mike.farrugia@gmail.com
License: MIT
Platform: UNKNOWN
Requires-Dist: six
Requires-Dist: findspark
Requires-Dist: pandas
Requires-Dist: sqlalchemy
Requires-Dist: dtest-framework
Requires-Dist: pyhamcrest
